class163/__init__.py
class163/common.py
class163/global_args.py
class163/login.py
class163/music.py
class163/origin_file.py
class163/playlist.py
class163/search.py
class163-0.7.7.1.dist-info/LICENSE
class163-0.7.7.1.dist-info/METADATA
class163-0.7.7.1.dist-info/WHEEL
class163-0.7.7.1.dist-info/top_level.txt
class163-0.7.7.1.dist-info/RECORD
