Metadata-Version: 2.1
Name: class163
Version: 0.7.7.1
Summary: 网易云音乐部分常用开放信息类API调用和部分需要用户凭证的API调用，包括音乐、歌单、搜索结果的获取，以及音乐的获取及信息写入。
Home-page: https://gitee.com/CooooldWind/class163
Author: CooooldWind_
Classifier: Development Status :: 4 - Beta
Classifier: Intended Audience :: Customer Service
Classifier: Intended Audience :: Developers
Classifier: Topic :: Communications :: File Sharing
Classifier: Topic :: Internet
Classifier: Topic :: Multimedia
Classifier: Topic :: Multimedia :: Graphics
Classifier: Topic :: Multimedia :: Sound/Audio
Classifier: Topic :: Multimedia :: Sound/Audio :: CD Audio
Classifier: Topic :: Multimedia :: Sound/Audio :: Editors
Classifier: License :: OSI Approved :: GNU Affero General Public License v3 or later (AGPLv3+)
Classifier: Programming Language :: Python :: 3.9
Classifier: Programming Language :: Python :: 3.10
Classifier: Programming Language :: Python :: 3.11
Classifier: Programming Language :: Python :: 3.12
Classifier: Programming Language :: Python :: 3.13
Classifier: Programming Language :: Python :: 3.14
License-File: LICENSE
Requires-Dist: netease_encode_api
Requires-Dist: typing_extensions
Requires-Dist: mutagen
Requires-Dist: pillow
